fastapi_boilerplate/__init__.py
fastapi_boilerplate/cli.py
fastapi_boilerplate/templates/__init__.py
fastapi_boilerplate/templates/base/__init__.py
fastapi_boilerplate/templates/base/main.py
fastapi_boilerplate/templates/base/routes/__init__.py
fastapi_boilerplate/templates/base/routes/test.py
fastapi_boilerplate/templates/mysql/database.py
fastapi_boilerplate/templates/mysql/main.py
fastapi_boilerplate_farhan-0.1.0.dist-info/licenses/LICENSE
fastapi_boilerplate_farhan-0.1.0.dist-info/METADATA
fastapi_boilerplate_farhan-0.1.0.dist-info/WHEEL
fastapi_boilerplate_farhan-0.1.0.dist-info/entry_points.txt
fastapi_boilerplate_farhan-0.1.0.dist-info/top_level.txt
fastapi_boilerplate_farhan-0.1.0.dist-info/RECORD
